excel_mcp/__main__.py
excel_mcp/browser.py
excel_mcp/calculations.py
excel_mcp/cell_utils.py
excel_mcp/cell_validation.py
excel_mcp/change_log.py
excel_mcp/chart.py
excel_mcp/data.py
excel_mcp/exceptions.py
excel_mcp/formatting.py
excel_mcp/pivot.py
excel_mcp/server.py
excel_mcp/sheet.py
excel_mcp/tables.py
excel_mcp/validation.py
excel_mcp/workbook.py
diligent_mcp_tools-1.0.2.dist-info/METADATA
diligent_mcp_tools-1.0.2.dist-info/WHEEL
diligent_mcp_tools-1.0.2.dist-info/entry_points.txt
diligent_mcp_tools-1.0.2.dist-info/licenses/LICENSE
diligent_mcp_tools-1.0.2.dist-info/RECORD
