Metadata-Version: 2.4
Name: diligent-mcp-tools
Version: 1.0.2
Summary: Excel & Browser automation tools for AI agents. 45 tools for reading/writing Excel files, creating charts, pivot tables, and full browser automation with Playwright.
Project-URL: Homepage, https://diligent4.com
Project-URL: Repository, https://github.com/Tslilon/flingoos-excel-mcp
Project-URL: Documentation, https://github.com/Tslilon/flingoos-excel-mcp#readme
Author-email: Diligent4 <maayan@diligent4.com>
License-Expression: MIT
License-File: LICENSE
Keywords: ai,automation,browser,claude,excel,mcp,model-context-protocol,playwright,spreadsheet
Classifier: Development Status :: 4 - Beta
Classifier: Intended Audience :: Developers
Classifier: License :: OSI Approved :: MIT License
Classifier: Operating System :: OS Independent
Classifier: Programming Language :: Python :: 3
Classifier: Programming Language :: Python :: 3.10
Classifier: Programming Language :: Python :: 3.11
Classifier: Programming Language :: Python :: 3.12
Classifier: Topic :: Office/Business :: Office Suites
Classifier: Topic :: Software Development :: Libraries :: Python Modules
Requires-Python: >=3.10
Requires-Dist: fastmcp<3.0.0,>=2.0.0
Requires-Dist: mcp[cli]>=1.10.1
Requires-Dist: openpyxl>=3.1.5
Requires-Dist: playwright>=1.40.0
Requires-Dist: pydantic>=2.0.0
Requires-Dist: typer>=0.16.0
